pinequiz/__init__.py
pinequiz/config_manager.py
pinequiz/crypto_util.py
pinequiz/pinequiz.py
pinequiz/quiz_engine.py
pinequiz/remote_loader.py
pinequiz-1.0.5.dist-info/licenses/LICENSE
pinequiz-1.0.5.dist-info/METADATA
pinequiz-1.0.5.dist-info/WHEEL
pinequiz-1.0.5.dist-info/entry_points.txt
pinequiz-1.0.5.dist-info/top_level.txt
pinequiz-1.0.5.dist-info/RECORD
