Metadata-Version: 2.4
Name: pinequiz
Version: 1.0.5
Summary: 🍍 PineQuiz CLI - Jalankan kuis terenkripsi dari GitHub
Home-page: https://github.com/openpineapletools/pinequiz
Author: openpineaplehub
Author-email: openpineaple@gmail.com
License: MIT
Project-URL: Source, https://github.com/openpineapletools/pinequiz
Project-URL: Bug Tracker, https://github.com/openpineapletools/pinequiz/issues
Keywords: cli quiz github kuis terminal encrypted
Classifier: Development Status :: 4 - Beta
Classifier: Environment :: Console
Classifier: Intended Audience :: Developers
Classifier: Topic :: Education
Classifier: Programming Language :: Python :: 3
Classifier: License :: OSI Approved :: MIT License
Classifier: Operating System :: OS Independent
Requires-Python: >=3.6
License-File: LICENSE
Requires-Dist: requests
Dynamic: author
Dynamic: author-email
Dynamic: classifier
Dynamic: description
Dynamic: description-content-type
Dynamic: home-page
Dynamic: keywords
Dynamic: license
Dynamic: license-file
Dynamic: project-url
Dynamic: requires-dist
Dynamic: requires-python
Dynamic: summary
